{
    "id": "elemental_arrows:blindness_arrow",
    "name": "Blindness Arrow",
    "item-model": "elemental_arrows:models/items/blindness_arrow.json",
    "entity-texture": "elemental_arrows:textures/entities/blindness_arrow",
    "events": {
        "arrow-hit-entity": {
            "actions": [
                {
                    "target": "hit-entity",
                    "function": {
                        "type": "add-potion-effects",
                        "data": {
                            "potion-effects": [
                                {
                                    "id": "minecraft:blindness",
                                    "amplifier": 12,
                                    "duration": 75
                                }
                            ]
                        }
                    }
                }
            ]
        }
    }
}